kitconcept.volto-1.4.0-py3.7-nspkg.pth
kitconcept/volto/__init__.py
kitconcept/volto/blocksuuidfixer.py
kitconcept/volto/configure.zcml
kitconcept/volto/controlpanel.py
kitconcept/volto/interfaces.py
kitconcept/volto/overrides.zcml
kitconcept/volto/patches.py
kitconcept/volto/patches.zcml
kitconcept/volto/scaling.py
kitconcept/volto/setuphandlers.py
kitconcept/volto/testing.py
kitconcept/volto/behaviors/__init__.py
kitconcept/volto/behaviors/configure.zcml
kitconcept/volto/behaviors/navtitle.py
kitconcept/volto/behaviors/preview.py
kitconcept/volto/cors/__init__.py
kitconcept/volto/cors/configure.zcml
kitconcept/volto/profiles/default/browserlayer.xml
kitconcept/volto/profiles/default/catalog.xml
kitconcept/volto/profiles/default/controlpanel.xml
kitconcept/volto/profiles/default/metadata.xml
kitconcept/volto/profiles/default/registry.xml
kitconcept/volto/profiles/default/types.xml
kitconcept/volto/profiles/default/types/Document.xml
kitconcept/volto/profiles/default/types/LRF.xml
kitconcept/volto/profiles/default/types/Plone_Site.xml
kitconcept/volto/profiles/homepage/metadata.xml
kitconcept/volto/profiles/richtext/metadata.xml
kitconcept/volto/profiles/richtext/types.xml
kitconcept/volto/profiles/richtext/types/Document.xml
kitconcept/volto/profiles/uninstall/browserlayer.xml
kitconcept/volto/tests/__init__.py
kitconcept/volto/tests/test_setup.py
kitconcept/volto/vocabularies/__init__.py
kitconcept/volto/vocabularies/configure.zcml
kitconcept/volto/vocabularies/subject.py
kitconcept.volto-1.4.0.dist-info/METADATA
kitconcept.volto-1.4.0.dist-info/WHEEL
kitconcept.volto-1.4.0.dist-info/entry_points.txt
kitconcept.volto-1.4.0.dist-info/namespace_packages.txt
kitconcept.volto-1.4.0.dist-info/top_level.txt
kitconcept.volto-1.4.0.dist-info/RECORD
